pxstatspy/__init__.py
pxstatspy/pxapi.py
pxstatspy-1.0.1.dist-info/licenses/LICENSE.md
pxstatspy-1.0.1.dist-info/METADATA
pxstatspy-1.0.1.dist-info/WHEEL
pxstatspy-1.0.1.dist-info/top_level.txt
pxstatspy-1.0.1.dist-info/RECORD
