Metadata-Version: 2.4
Name: pxstatspy
Version: 1.0.1
Summary: A Python wrapper for the Statistics Sweden PxWebAPI 2.0
Author-email: Emanuel Raptis <emanuelraptis@gmail.com>
License: MIT License
Project-URL: Homepage, https://github.com/xemarap/pxstatspy
Project-URL: Documentation, https://github.com/xemarap/pxstatspy/blob/main/README.md
Project-URL: Repository, https://github.com/xemarap/pxstatspy
Project-URL: Bug Tracker, https://github.com/xemarap/pxstatspy/issues
Keywords: statistics,sweden,api,data,px
Classifier: Programming Language :: Python :: 3
Classifier: Programming Language :: Python :: 3.7
Classifier: Programming Language :: Python :: 3.8
Classifier: Programming Language :: Python :: 3.9
Classifier: Programming Language :: Python :: 3.10
Classifier: Programming Language :: Python :: 3.11
Classifier: Programming Language :: Python :: 3.12
Classifier: Programming Language :: Python :: 3.13
Classifier: Operating System :: OS Independent
Classifier: Development Status :: 4 - Beta
Classifier: Intended Audience :: Developers
Classifier: Intended Audience :: Science/Research
Classifier: Topic :: Software Development :: Libraries :: Python Modules
Requires-Python: >=3.7
License-File: LICENSE.md
Requires-Dist: requests>=2.25.0
Requires-Dist: pandas>=1.1.0
Provides-Extra: dev
Requires-Dist: pytest>=6.0.0; extra == "dev"
Dynamic: license-file
